usd_qtpy/__init__.py
usd_qtpy/__main__.py
usd_qtpy/editor.py
usd_qtpy/layer_diff.py
usd_qtpy/layer_editor.py
usd_qtpy/prim_delegate.py
usd_qtpy/prim_hierarchy.py
usd_qtpy/prim_hierarchy_cache.py
usd_qtpy/prim_hierarchy_model.py
usd_qtpy/prim_spec_editor.py
usd_qtpy/prim_type_icons.py
usd_qtpy/references.py
usd_qtpy/variants.py
usd_qtpy/version.py
usd_qtpy/viewer.py
usd_qtpy/lib/__init__.py
usd_qtpy/lib/qt.py
usd_qtpy/lib/usd.py
usd_qtpy/lib/usd_merge_spec.py
usd_qtpy/resources/__init__.py
usd_qtpy/resources/feathericons/LICENSE.txt
usd_qtpy/resources/feathericons/box.svg
usd_qtpy/resources/feathericons/crosshair.svg
usd_qtpy/resources/feathericons/edit-2.svg
usd_qtpy/resources/feathericons/folder.svg
usd_qtpy/resources/feathericons/globe.svg
usd_qtpy/resources/feathericons/help-circle.svg
usd_qtpy/resources/feathericons/map.svg
usd_qtpy/resources/feathericons/move.svg
usd_qtpy/resources/feathericons/plus.svg
usd_qtpy/resources/feathericons/save.svg
usd_qtpy/resources/feathericons/sun.svg
usd_qtpy/resources/feathericons/target.svg
usd_qtpy/resources/feathericons/video.svg
usd_qtpy/resources/feathericons/wind.svg
usd_qtpy/resources/feathericons/x.svg
usd_qtpy/resources/feathericons/zap.svg
usd_qtpy/style/LICENSE
usd_qtpy/style/__init__.py
usd_qtpy/style/color_defs.py
usd_qtpy/style/data.json
usd_qtpy/style/pyqt5_resources.py
usd_qtpy/style/pyside2_resources.py
usd_qtpy/style/pyside6_resources.py
usd_qtpy/style/qrc_resources.py
usd_qtpy/style/resources.qrc
usd_qtpy/style/style.css
usd_qtpy/style/fonts/Noto_Sans/NotoSans-Bold.ttf
usd_qtpy/style/fonts/Noto_Sans/NotoSans-BoldItalic.ttf
usd_qtpy/style/fonts/Noto_Sans/NotoSans-Italic.ttf
usd_qtpy/style/fonts/Noto_Sans/NotoSans-Regular.ttf
usd_qtpy/style/fonts/Noto_Sans/OFL.txt
"usd_qtpy/style/fonts/Noto_Sans_Mono/NotoSansMono-VariableFont_wdth,wght.ttf"
usd_qtpy/style/fonts/Noto_Sans_Mono/OFL.txt
usd_qtpy/style/fonts/Noto_Sans_Mono/README.txt
usd_qtpy/style/fonts/Noto_Sans_Mono/static/NotoSansMono/NotoSansMono-Black.ttf
usd_qtpy-0.0.3.dist-info/LICENSE
usd_qtpy-0.0.3.dist-info/METADATA
usd_qtpy-0.0.3.dist-info/WHEEL
usd_qtpy-0.0.3.dist-info/top_level.txt
usd_qtpy-0.0.3.dist-info/RECORD
