Metadata-Version: 2.1
Name: usd-qtpy
Version: 0.0.3
Summary: Python Qt components for building custom USD tools.
Author: BigRoy, Hannes
License: MIT License
Project-URL: Homepage, https://github.com/BigRoy/usd-qtpy
Project-URL: Documentation, https://github.com/BigRoy/usd-qtpy
Project-URL: Issues, https://github.com/BigRoy/usd-qtpy/issues
Keywords: usd,qt
Classifier: Programming Language :: Python :: 3.9
Classifier: License :: OSI Approved :: MIT License
Classifier: Operating System :: OS Independent
Requires-Python: >=3.8
License-File: LICENSE
Requires-Dist: qtpy
Provides-Extra: usd
Requires-Dist: usd-core ; extra == 'usd'
Provides-Extra: usdview
Requires-Dist: PyOpenGL ; extra == 'usdview'
